<RawMarkup>
	<Version Version="1" Revision="0"/>
	<RawPictures/>
	<Barcodes/>
	<RawObjects>
		<RawObject Name="Блик" ClassName="Блик" Comment="" Page="1">
			<RawRect TopLeftX="1207" TopLeftY="680" TopRightX="2459" TopRightY="680" BottomLeftX="1207" BottomLeftY="800" BottomRightX="2459" BottomRightY="800" />
			<Polygon Points="[1207.92131541755, 731.64398636949]; [1242.11028674323, 800.021929020844]; [1693.40470824217, 800.021929020844]; [2035.29442149894, 789.765237623141]; [2459.23766593733, 789.765237623141]; [2349.83295769517, 714.549500706651]; [1895.11963906366, 711.130603574083]; [1731.01257670041, 680.360529380974]; [1519.04095448121, 707.711706441516]"/>
		</RawObject>
		<RawObject Name="Блик" ClassName="Блик" Comment="" Page="1">
			<RawRect TopLeftX="1088" TopLeftY="1353" TopRightX="2257" TopRightY="1353" BottomLeftX="1088" BottomLeftY="1511" BottomRightX="2257" BottomRightY="1511" />
			<Polygon Points="[1088.25991577768, 1449.61238420871]; [1248.94808100836, 1511.15253259493]; [1519.04095448121, 1511.15253259493]; [1860.93066773798, 1487.22025266695]; [2257.52273511584, 1432.51789854587]; [2059.22670142691, 1353.88326449681]; [1809.64721074947, 1374.39664729222]; [1423.31183476932, 1398.32892722019]; [1218.17800681526, 1398.32892722019]"/>
		</RawObject>
	</RawObjects>
</RawMarkup>
