<RawMarkup>
	<Version Version="1" Revision="0"/>
	<RawPictures/>
	<Barcodes/>
	<RawObjects>
		<RawObject Name="Блик" ClassName="Блик" Comment="" Page="1">
			<RawRect TopLeftX="1089" TopLeftY="827" TopRightX="1618" TopRightY="827" BottomLeftX="1089" BottomLeftY="1367" BottomRightX="1618" BottomRightY="1367" />
			<Polygon Points="[1325.25576185139, 827.423410877696]; [1247.71517488476, 835.731330909835]; [1170.17458791812, 874.501624393153]; [1109.24984101577, 927.11845126337]; [1089.86469427411, 1026.81349164904]; [1109.24984101577, 1123.73922535734]; [1139.71221446694, 1198.51050564659]; [1167.40528124074, 1287.12831932275]; [1319.71714849663, 1367.43821296677]; [1427.72010891445, 1342.51445287035]; [1516.3379225906, 1284.35901264537]; [1618.80226965366, 1223.43426574301]; [1563.41613610606, 1162.50951884066]; [1519.10722926798, 1101.5847719383]; [1485.87554913942, 1001.88973155263]; [1480.33693578467, 960.350131391928]; [1469.25970907515, 896.656077812192]; [1430.48941559183, 863.424397683634]; [1383.41120207637, 849.577864296734]"/>
		</RawObject>
	</RawObjects>
</RawMarkup>
