<RawMarkup>
	<Version Version="1" Revision="0"/>
	<RawPictures/>
	<Barcodes/>
	<RawObjects>
		<RawObject Name="Блик" ClassName="Блик" Comment="" Page="1">
			<RawRect TopLeftX="183" TopLeftY="709" TopRightX="1503" TopRightY="709" BottomLeftX="183" BottomLeftY="828" BottomRightX="1503" BottomRightY="828" />
			<Polygon Points="[183.441690923442, 786.614940714231]; [313.904656700436, 725.220603877999]; [544.133419836309, 721.383457825734]; [885.639418487853, 709.872019668941]; [1054.47384478749, 736.732042034792]; [1300.05119213242, 729.057749930263]; [1503.41993290244, 782.777794661967]; [1334.58550660281, 828.823547289142]; [1004.59094610805, 817.312109132348]; [793.547913233504, 821.149255184612]; [551.807711940838, 828.823547289142]; [402.159015902521, 809.637817027819]"/>
		</RawObject>
		<RawObject Name="Блик" ClassName="Блик" Comment="" Page="1">
			<RawRect TopLeftX="1898" TopLeftY="1711" TopRightX="2186" TopRightY="1711" BottomLeftX="1898" BottomLeftY="1791" BottomRightX="2186" BottomRightY="1791" />
			<Polygon Points="[1898.64597628569, 1757.41289193716]; [2044.45752627175, 1791.94720640754]; [2186.43193020553, 1788.11006035528]; [2182.59478415327, 1730.55286957131]; [2075.15469468986, 1711.36713930999]"/>
		</RawObject>
		<RawObject Name="Блик" ClassName="Блик" Comment="" Page="1">
			<RawRect TopLeftX="275" TopLeftY="1454" TopRightX="1449" TopRightY="1454" BottomLeftX="275" BottomLeftY="2432" BottomRightX="1449" BottomRightY="2432" />
			<Polygon Points="[275.533196177791, 2279.26475504514]; [467.390498791018, 2206.35898005211]; [597.853464568013, 2110.4303287455]; [716.804992188213, 1930.08446428907]; [720.642138240478, 1788.11006035528]; [689.944969822361, 1684.50711694413]; [609.364902724806, 1615.43848800337]; [425.181892216108, 1546.36985906261]; [524.947689574986, 1496.48696038317]; [701.456407979155, 1481.13837617411]; [889.476564540118, 1454.27835380826]; [1000.75380005579, 1473.46408406958]; [1181.09966451222, 1542.53271301035]; [1277.02831581884, 1630.78707221243]; [1434.35130396168, 1742.0643077281]; [1449.69988817074, 2002.99023928209]; [1372.95696712545, 2210.19612610438]; [1219.47112503487, 2359.84482214269]; [1008.42809216032, 2421.23915897893]; [808.896497442562, 2432.75059713572]; [532.621981679515, 2367.51911424722]; [386.810431693463, 2325.31050767231]"/>
		</RawObject>
		<RawObject Name="Блик" ClassName="Блик" Comment="" Page="1">
			<RawRect TopLeftX="22" TopLeftY="1837" TopRightX="260" TopRightY="1837" BottomLeftX="22" BottomLeftY="2474" BottomRightX="260" BottomRightY="2474" />
			<Polygon Points="[260.184611968733, 1837.99295903472]; [252.510319864204, 2474.95920371063]; [129.721646191738, 2444.26203529251]; [41.4672869896538, 2317.63621556778]; [22.281556728331, 2167.98751952947]; [49.1415790941828, 2075.89601427512]; [60.6530172509763, 1991.4788011253]; [148.907376453061, 1918.57302613227]"/>
		</RawObject>
	</RawObjects>
</RawMarkup>
