<RawMarkup>
	<Version Version="1" Revision="0"/>
	<RawPictures/>
	<Barcodes/>
	<RawObjects>
		<RawObject Name="Блик" ClassName="Блик" Comment="" Page="1">
			<RawRect TopLeftX="632" TopLeftY="1606" TopRightX="1702" TopRightY="1606" BottomLeftX="632" BottomLeftY="2610" BottomRightX="1702" BottomRightY="2610" />
			<Polygon Points="[1045.93108071689, 1787.41382536919]; [1184.78757601576, 1655.50015483527]; [1372.24384466923, 1606.90038148067]; [1552.75728855776, 1697.15710342493]; [1590.94282476494, 1960.98444449278]; [1483.32904090832, 2203.98331126579]; [1441.67209231866, 2398.38240468421]; [1702.02802100404, 2610.13856001498]; [632.833007202762, 2540.71031236555]; [712.675491999611, 2231.75461032557]; [861.946224445893, 1985.28433117008]"/>
		</RawObject>
		<RawObject Name="Блик" ClassName="Блик" Comment="" Page="1">
			<RawRect TopLeftX="632" TopLeftY="812" TopRightX="1257" TopRightY="812" BottomLeftX="632" BottomLeftY="1499" BottomRightX="1257" BottomRightY="1499" />
			<Polygon Points="[1257.68723604766, 1339.96517963406]; [1122.30215313127, 1235.82280815991]; [1038.98825595195, 1110.85196239093]; [976.502833067458, 923.395693737464]; [962.617183537571, 812.310497498371]; [632.833007202762, 1138.62326145071]; [830.703513003647, 1194.16585957025]; [948.731534007684, 1499.65014922776]"/>
		</RawObject>
		<RawObject Name="Блик" ClassName="Блик" Comment="" Page="1">
			<RawRect TopLeftX="1237" TopLeftY="285" TopRightX="2028" TopRightY="285" BottomLeftX="1237" BottomLeftY="759" BottomRightX="2028" BottomRightY="759" />
			<Polygon Points="[1237.62250674723, 417.802329541175]; [1317.78476180787, 348.32837515529]; [1412.19808443484, 312.700706239451]; [1510.1741739534, 285.979954552572]; [1604.58749658037, 287.761337998364]; [1723.94018744843, 305.575172456283]; [1823.69766041278, 360.798059275833]; [1896.73438169025, 412.458179203799]; [1950.17588506401, 473.025216360725]; [1992.92908776301, 553.187471421362]; [2026.77537323306, 649.382177494127]; [2028.55675667885, 759.827951133227]; [2000.05462154618, 617.317275469872]; [1957.30141884717, 530.029486626067]; [1907.422682365, 465.899682577558]; [1846.85564520807, 410.676795758008]; [1780.94445771377, 360.798059275833]; [1686.5311350868, 325.170390359995]; [1567.17844421874, 303.793789010491]; [1478.10927192914, 319.826240022619]; [1378.35179896479, 342.984224817914]; [1308.87784457891, 380.393277179545]"/>
		</RawObject>
		<RawObject Name="Блик" ClassName="Блик" Comment="" Page="1">
			<RawRect TopLeftX="1385" TopLeftY="333" TopRightX="1954" TopRightY="333" BottomLeftX="1385" BottomLeftY="605" BottomRightX="1954" BottomRightY="605" />
			<Polygon Points="[1385.1607451019, 376.349301932786]; [1453.29644140977, 345.931580366774]; [1514.13188454179, 334.98120060301]; [1607.81846696511, 333.76449174037]; [1671.08732782242, 348.364998092055]; [1751.39011275669, 376.349301932786]; [1814.658973614, 412.850567812001]; [1870.62758129546, 463.952340042901]; [1920.51264466372, 519.920947724364]; [1954.58049281765, 605.090568109198]; [1908.34555603731, 527.221200900207]; [1865.7607458449, 477.336137531947]; [1814.658973614, 433.534618476889]; [1741.65644185557, 393.383226009753]; [1675.95416327298, 366.615631031663]; [1596.86808720135, 350.798415817336]; [1510.48175795387, 350.798415817336]; [1436.2625173328, 370.265757619584]"/>
		</RawObject>
		<RawObject Name="Блик" ClassName="Блик" Comment="" Page="1">
			<RawRect TopLeftX="1674" TopLeftY="390" TopRightX="1844" TopRightY="390" BottomLeftX="1674" BottomLeftY="491" BottomRightX="1844" BottomRightY="491" />
			<Polygon Points="[1674.72739896519, 390.758754826702]; [1722.99353566498, 403.830833516228]; [1765.2264052773, 420.92509026407]; [1808.46481940419, 452.096970216016]; [1844.66442192903, 491.313206284594]; [1798.4093742584, 454.108059245174]; [1760.1986827044, 431.986079924438]; [1725.00462469414, 416.902912205754]"/>
		</RawObject>
		<RawObject Name="Блик" ClassName="Блик" Comment="" Page="1">
			<RawRect TopLeftX="1450" TopLeftY="582" TopRightX="1733" TopRightY="582" BottomLeftX="1450" BottomLeftY="821" BottomRightX="1733" BottomRightY="821" />
			<Polygon Points="[1450.47262199155, 641.002860216951]; [1479.25941046771, 603.00429942841]; [1517.25797125626, 584.580754803663]; [1566.77124743526, 582.27781172557]; [1631.25365362188, 590.338112498897]; [1678.46398672279, 615.670486357924]; [1701.49341750372, 642.154331755998]; [1721.06843366752, 689.364664856912]; [1733.73462059703, 740.029412574966]; [1706.09930365991, 821.783891847281]; [1714.15960443324, 731.969111801639]; [1695.73605980849, 682.455835622632]; [1663.49485671518, 643.305803295044]; [1618.58746669236, 619.124900975064]; [1567.92271897431, 606.45871404555]; [1519.56091433435, 609.91312866269]; [1482.71382508485, 626.033730209344]"/>
		</RawObject>
		<RawObject Name="Блик" ClassName="Блик" Comment="" Page="1">
			<RawRect TopLeftX="1334" TopLeftY="631" TopRightX="1423" TopRightY="631" BottomLeftX="1334" BottomLeftY="794" BottomRightX="1423" BottomRightY="794" />
			<Polygon Points="[1334.17399654783, 794.14857491016]; [1402.11081735159, 773.42208720732]; [1403.26228889063, 715.848510254986]; [1423.98877659347, 660.577876380745]; [1372.17255733637, 631.791087904577]; [1334.17399654783, 696.273494091192]"/>
		</RawObject>
		<RawObject Name="Блик" ClassName="Блик" Comment="" Page="1">
			<RawRect TopLeftX="1329" TopLeftY="812" TopRightX="1769" TopRightY="812" BottomLeftX="1329" BottomLeftY="1030" BottomRightX="1769" BottomRightY="1030" />
			<Polygon Points="[1338.77988270402, 822.935363386327]; [1399.80787427349, 812.572119534907]; [1438.95790660108, 864.388338792008]; [1479.25941046771, 895.478070346268]; [1529.92415818577, 906.992785736735]; [1582.89184898192, 908.144257275782]; [1623.19335284855, 896.629541885315]; [1664.64632825423, 875.903054182475]; [1700.34194596468, 834.450078776794]; [1769.43023830748, 848.267737245354]; [1740.64344983131, 904.689842658642]; [1691.1301736523, 942.688403447183]; [1619.73893823141, 972.626663462396]; [1572.5286051305, 985.29285039191]; [1543.74181665433, 1030.20024041473]; [1485.01676816295, 1018.68552502426]; [1427.44319121061, 1000.26198039952]; [1384.83874426589, 970.323720384303]; [1362.960785024, 944.991346525276]; [1329.56811039165, 912.750143431969]; [1350.29459809449, 862.085395713915]"/>
		</RawObject>
		<RawObject Name="Блик" ClassName="Блик" Comment="" Page="1">
			<RawRect TopLeftX="1049" TopLeftY="836" TopRightX="1759" TopRightY="836" BottomLeftX="1049" BottomLeftY="1319" BottomRightX="1759" BottomRightY="1319" />
			<Polygon Points="[1093.55518143266, 836.434415032968]; [1049.15868842748, 987.71135416172]; [1090.26655232116, 1083.08159839506]; [1174.12659466428, 1183.38478629565]; [1249.76506422865, 1236.00285207956]; [1310.6047027913, 1267.24482863876]; [1368.15571224246, 1280.39934508474]; [1430.63966536086, 1303.4197488652]; [1521.07696592696, 1316.57426531118]; [1618.09152471605, 1319.86289442268]; [1759.50257651032, 1290.26523241922]; [1759.50257651032, 1170.23026984967]; [1637.82329938502, 1203.11656096462]; [1534.23148237294, 1211.33813374335]; [1430.63966536086, 1186.67341540714]; [1335.26942112751, 1150.4984951807]; [1221.81171678095, 1073.21571106058]; [1167.54933644129, 999.221556051951]; [1124.79715799186, 910.428570041597]"/>
		</RawObject>
		<RawObject Name="Блик" ClassName="Блик" Comment="" Page="1">
			<RawRect TopLeftX="1319" TopLeftY="996" TopRightX="1436" TopRightY="996" BottomLeftX="1319" BottomLeftY="1112" BottomRightX="1436" BottomRightY="1112" />
			<Polygon Points="[1436.0856298214, 1054.63474533219]; [1428.27232502777, 1083.79439579704]; [1406.92597935656, 1105.14074146825]; [1377.76632889172, 1112.95404626188]; [1348.60667842687, 1105.14074146825]; [1327.26033275566, 1083.79439579704]; [1319.44702796203, 1054.63474533219]; [1327.26033275566, 1025.47509486735]; [1348.60667842687, 1004.12874919613]; [1377.76632889172, 996.315444402506]; [1406.92597935656, 1004.12874919613]; [1428.27232502777, 1025.47509486735]"/>
		</RawObject>
	</RawObjects>
</RawMarkup>
