<RawMarkup>
	<Version Version="1" Revision="0"/>
	<RawPictures/>
	<Barcodes/>
	<RawObjects>
		<RawObject Name="Блик" ClassName="Блик" Comment="" Page="1">
			<RawRect TopLeftX="167" TopLeftY="3324" TopRightX="1707" TopRightY="3324" BottomLeftX="167" BottomLeftY="3487" BottomRightX="1707" BottomRightY="3487" />
			<Polygon Points="[167.532862249453, 3374.29191328243]; [199.244813094614, 3465.90421572401]; [533.982072015763, 3487.04551628745]; [984.996484035838, 3455.33356544228]; [1383.15764464731, 3441.23936506666]; [1707.32425328674, 3398.95676393978]; [1524.09964840358, 3367.24481309461]; [1235.16854070322, 3349.62706262508]; [865.195780843006, 3324.96221196773]; [495.223020982788, 3346.10351253117]"/>
		</RawObject>
		<RawObject Name="Блик" ClassName="Блик" Comment="" Page="1">
			<RawRect TopLeftX="660" TopLeftY="3131" TopRightX="1319" TopRightY="3131" BottomLeftX="660" BottomLeftY="3169" BottomRightX="1319" BottomRightY="3169" />
			<Polygon Points="[660.82987539641, 3141.73760708458]; [907.478381969888, 3134.69050689676]; [1192.88593957634, 3131.16695680286]; [1319.73374295699, 3145.26115717848]; [1192.88593957634, 3169.92600783583]; [903.954831875981, 3166.40245774192]"/>
		</RawObject>
		<RawObject Name="Блик" ClassName="Блик" Comment="" Page="1">
			<RawRect TopLeftX="2732" TopLeftY="3138" TopRightX="2901" TopRightY="3138" BottomLeftX="2732" BottomLeftY="3184" BottomRightX="2901" BottomRightY="3184" />
			<Polygon Points="[2732.67733061363, 3169.92600783583]; [2817.24253286739, 3138.21405699067]; [2901.80773512116, 3159.35535755411]; [2827.81318314911, 3184.02020821146]"/>
		</RawObject>
		<RawObject Name="Блик" ClassName="Блик" Comment="" Page="1">
			<RawRect TopLeftX="2736" TopLeftY="2750" TopRightX="2859" TopRightY="2750" BottomLeftX="2736" BottomLeftY="2880" BottomRightX="2859" BottomRightY="2880" />
			<Polygon Points="[2736.20088070753, 2750.62354666092]; [2796.10123230395, 2796.42969788171]; [2859.52513399427, 2880.99490013547]; [2764.38928145879, 2842.2358491025]"/>
		</RawObject>
		<RawObject Name="Блик" ClassName="Блик" Comment="" Page="1">
			<RawRect TopLeftX="713" TopLeftY="3043" TopRightX="1467" TopRightY="3043" BottomLeftX="713" BottomLeftY="3078" BottomRightX="1467" BottomRightY="3078" />
			<Polygon Points="[713.683126805012, 3053.64885473691]; [907.478381969888, 3043.07820445519]; [1245.73919098494, 3043.07820445519]; [1467.72284690107, 3057.17240483081]; [1231.64499060932, 3078.31370539425]; [893.384181594261, 3074.79015530035]"/>
		</RawObject>
		<RawObject Name="Блик" ClassName="Блик" Comment="" Page="1">
			<RawRect TopLeftX="287" TopLeftY="2866" TopRightX="442" TopRightY="2866" BottomLeftX="287" BottomLeftY="3014" BottomRightX="442" BottomRightY="3014" />
			<Polygon Points="[287.333565442285, 3014.88980370393]; [357.804567320422, 2965.56010238923]; [396.563618353397, 2866.90069975984]; [442.369769574186, 2926.80105135626]; [403.610718541211, 2983.17785285877]"/>
		</RawObject>
		<RawObject Name="Блик" ClassName="Блик" Comment="" Page="1">
			<RawRect TopLeftX="477" TopLeftY="2447" TopRightX="1735" TopRightY="2447" BottomLeftX="477" BottomLeftY="3000" BottomRightX="1735" BottomRightY="3000" />
			<Polygon Points="[569.217572954832, 2447.59823858493]; [706.636026617198, 2666.05834440715]; [731.300877274546, 2803.47679806952]; [696.065376335478, 2954.98945210751]; [477.605270513254, 3000.7956033283]; [710.159576711105, 2990.22495304658]; [868.719330936913, 2965.56010238923]; [1735.51265403799, 2983.17785285877]; [1488.86414746452, 2852.80649938422]; [1390.20474483512, 2909.18330088673]; [1006.13778459928, 2683.67609487669]; [791.201228870962, 2486.35728961791]"/>
		</RawObject>
		<RawObject Name="Блик" ClassName="Блик" Comment="" Page="1">
			<RawRect TopLeftX="114" TopLeftY="1129" TopRightX="1686" TopRightY="1129" BottomLeftX="114" BottomLeftY="2475" BottomRightX="1686" BottomRightY="2475" />
			<Polygon Points="[114.67961084085, 2000.10737665876]; [248.57451440931, 2116.38452975769]; [290.857115536192, 2165.71423107238]; [336.663266756981, 2236.18523295052]; [417.704918916838, 2239.70878304443]; [576.264673142646, 2271.42073388959]; [734.824427368453, 2303.13268473475]; [829.960279903938, 2363.03303633117]; [932.143232627236, 2394.74498717633]; [1058.99103600788, 2415.88628773977]; [1189.36238948243, 2472.26308924228]; [1326.7808431448, 2475.78663933619]; [1439.53444614982, 2398.26853727023]; [1432.48734596201, 2246.75588323224]; [1481.8170472767, 2021.2486772222]; [1481.8170472767, 1816.88277177561]; [1686.1829527233, 1778.12372074263]; [1397.25184502294, 1612.51686632901]; [1231.64499060932, 1429.29226144586]; [1273.9275917362, 1129.79050346377]; [385.992968071676, 1147.40825393331]; [512.840771452322, 1355.29770947381]; [674.924075772037, 1376.43901003725]; [777.107028495335, 1506.81036351181]; [787.677678777055, 1637.18171698636]; [674.924075772037, 1668.89366783152]; [583.311773330459, 1686.51141830105]; [502.270121170602, 1693.55851848887]; [407.134268635117, 1711.1762689584]; [262.668714784937, 1739.36466970966]; [266.192264878844, 1912.01862431109]"/>
		</RawObject>
		<RawObject Name="Блик" ClassName="Блик" Comment="" Page="1">
			<RawRect TopLeftX="450" TopLeftY="2377" TopRightX="517" TopRightY="2377" BottomLeftX="450" BottomLeftY="2723" BottomRightX="517" BottomRightY="2723" />
			<Polygon Points="[450.639920207818, 2377.4475594426]; [503.056367885771, 2453.16020608854]; [517.616492240758, 2528.87285273447]; [511.792442498764, 2633.70574809037]; [471.0240943048, 2723.97851909129]; [476.848144046795, 2642.44182270337]; [485.584218659787, 2555.08107657344]; [471.0240943048, 2467.72033044352]"/>
		</RawObject>
		<RawObject Name="Блик" ClassName="Блик" Comment="" Page="1">
			<RawRect TopLeftX="2643" TopLeftY="2118" TopRightX="2716" TopRightY="2118" BottomLeftX="2643" BottomLeftY="2409" BottomRightX="2716" BottomRightY="2409" />
			<Polygon Points="[2716.19526984378, 2118.27734592384]; [2655.04274755284, 2223.11024127974]; [2643.39464806885, 2313.38301228066]; [2660.86679729483, 2409.47983302358]; [2666.69084703683, 2362.88743508762]; [2681.25097139181, 2272.6146640867]; [2687.07502113381, 2202.72606718276]"/>
		</RawObject>
		<RawObject Name="Блик" ClassName="Блик" Comment="" Page="1">
			<RawRect TopLeftX="2323" TopLeftY="1930" TopRightX="2581" TopRightY="1930" BottomLeftX="2323" BottomLeftY="2425" BottomRightX="2581" BottomRightY="2425" />
			<Polygon Points="[2323.04086904448, 2020.69098116921]; [2356.78299740211, 2141.6002744507]; [2379.27774964052, 2279.380631911]; [2390.52512575973, 2425.5965214607]; [2500.18704292201, 2417.1609893713]; [2581.73051978627, 2405.91361325209]; [2581.73051978627, 2329.99382444743]; [2581.73051978627, 2178.15424683812]; [2553.61207948825, 1953.20672445396]; [2452.38569441538, 1930.71197221554]; [2376.46590561072, 1956.01856848376]"/>
		</RawObject>
		<RawObject Name="Блик" ClassName="Блик" Comment="" Page="1">
			<RawRect TopLeftX="209" TopLeftY="2855" TopRightX="338" TopRightY="2855" BottomLeftX="209" BottomLeftY="3006" BottomRightX="338" BottomRightY="3006" />
			<Polygon Points="[209.337476434959, 3006.86869359592]; [263.112241023756, 2922.36549209924]; [295.761205238382, 2883.95494596439]; [338.012805986723, 2855.14703636324]; [314.96647830581, 2907.0012736453]; [272.71487755747, 2947.3323470869]"/>
		</RawObject>
		<RawObject Name="Блик" ClassName="Блик" Comment="" Page="1">
			<RawRect TopLeftX="401" TopLeftY="2344" TopRightX="434" TopRightY="2344" BottomLeftX="401" BottomLeftY="2666" BottomRightX="434" BottomRightY="2666" />
			<Polygon Points="[401.390207109234, 2344.28677276967]; [418.674952869918, 2421.10786503938]; [434.03917132386, 2488.32632077538]; [432.118644017118, 2580.51163149903]; [414.833898256433, 2666.93536030246]; [418.674952869918, 2580.51163149903]; [416.754425563176, 2492.16737538887]; [403.310734415976, 2392.29995543824]"/>
		</RawObject>
		<RawObject Name="Блик" ClassName="Блик" Comment="" Page="1">
			<RawRect TopLeftX="0" TopLeftY="2371" TopRightX="65" TopRightY="2371" BottomLeftX="0" BottomLeftY="2641" BottomRightX="65" BottomRightY="2641" />
			<Polygon Points="[0, 2371.17415506407]; [3.84105461348543, 2641.9685053148]; [49.9337099753114, 2617.00165032714]; [65.2979284292534, 2532.49844883046]; [59.5363465090252, 2472.96210232144]; [46.0926553618259, 2421.10786503938]; [30.728436907884, 2392.29995543824]"/>
		</RawObject>
		<RawObject Name="Блик" ClassName="Блик" Comment="" Page="1">
			<RawRect TopLeftX="151" TopLeftY="2108" TopRightX="347" TopRightY="2108" BottomLeftX="151" BottomLeftY="2903" BottomRightX="347" BottomRightY="2903" />
			<Polygon Points="[151.721657232677, 2108.06191404032]; [224.701694888901, 2248.26040743254]; [280.396986784441, 2398.06153735847]; [289.999623318154, 2526.73686691023]; [270.794350250727, 2655.412196462]; [251.5890771833, 2770.64383486656]; [207.416949128217, 2903.16021903181]; [303.443314465354, 2782.16699870702]; [328.410169453009, 2676.53799683617]; [347.615442520437, 2555.54477651138]; [339.933333293466, 2411.50522850567]; [316.887005612553, 2340.44571815619]; [272.71487755747, 2240.57829820557]; [215.099058355187, 2144.55193286843]"/>
		</RawObject>
		<RawObject Name="Блик" ClassName="Блик" Comment="" Page="1">
			<RawRect TopLeftX="69" TopLeftY="2426" TopRightX="192" TopRightY="2426" BottomLeftX="69" BottomLeftY="2578" BottomRightX="192" BottomRightY="2578" />
			<Polygon Points="[69.1389830427388, 2438.39261080007]; [172.847457606847, 2426.86944695961]; [192.052730674274, 2520.97528499001]; [86.4237288034235, 2578.59110419229]; [90.264783416909, 2501.77001192258]"/>
		</RawObject>
		<RawObject Name="Блик" ClassName="Блик" Comment="" Page="1">
			<RawRect TopLeftX="2703" TopLeftY="2151" TopRightX="2755" TopRightY="2151" BottomLeftX="2703" BottomLeftY="2436" BottomRightX="2755" BottomRightY="2436" />
			<Polygon Points="[2751.73593078562, 2151.55969792161]; [2755.89857147776, 2220.24326934198]; [2743.41064940133, 2307.658723877]; [2728.84140697883, 2390.91153771988]; [2708.02820351811, 2436.70058533346]; [2703.86556282596, 2353.44777149058]; [2712.19084421025, 2243.13779314877]"/>
		</RawObject>
		<RawObject Name="Блик" ClassName="Блик" Comment="" Page="1">
			<RawRect TopLeftX="2778" TopLeftY="2003" TopRightX="2903" TopRightY="2003" BottomLeftX="2778" BottomLeftY="2488" BottomRightX="2903" BottomRightY="2488" />
			<Polygon Points="[2903.67231604887, 2003.7859533505]; [2893.26571431851, 2035.00575854158]; [2862.04590912743, 2089.12008753945]; [2824.58214289813, 2166.12894034411]; [2799.60629874527, 2247.30043384091]; [2801.68761909134, 2311.82136456914]; [2789.19969701491, 2388.8302173738]; [2799.60629874527, 2488.73359398526]; [2780.87441563062, 2409.64342083452]; [2778.79309528455, 2299.33344249271]; [2797.5249783992, 2191.10478449697]; [2824.58214289813, 2114.09593169231]; [2866.20854981957, 2041.24971957979]"/>
		</RawObject>
		<RawObject Name="Блик" ClassName="Блик" Comment="" Page="1">
			<RawRect TopLeftX="2814" TopLeftY="2692" TopRightX="3028" TopRightY="2692" BottomLeftX="2814" BottomLeftY="2869" BottomRightX="3028" BottomRightY="2869" />
			<Polygon Points="[2814.17554116777, 2692.7029879003]; [2899.50967535672, 2736.41071516781]; [2989.00645023781, 2815.50088831855]; [3028.55153681318, 2869.61521731642]; [2947.38004331638, 2848.8020138557]; [2887.02175328029, 2798.85032554997]; [2837.07006497456, 2746.81731689817]"/>
		</RawObject>
		<RawObject Name="Блик" ClassName="Блик" Comment="" Page="1">
			<RawRect TopLeftX="3111" TopLeftY="2213" TopRightX="3165" TopRightY="2213" BottomLeftX="3111" BottomLeftY="2519" BottomRightX="3165" BottomRightY="2519" />
			<Polygon Points="[3163.83735930786, 2245.21911349484]; [3165.91867965393, 2213.99930830376]; [3134.69887446285, 2253.54439487913]; [3113.88567100213, 2332.63456802986]; [3111.80435065606, 2390.91153771988]; [3134.69887446285, 2465.83907017846]; [3165.91867965393, 2519.95339917633]; [3165.91867965393, 2478.3269922549]; [3138.86151515499, 2430.45662429524]; [3134.69887446285, 2370.09833425916]; [3136.78019480892, 2320.14664595343]; [3140.94283550107, 2280.60155937806]"/>
		</RawObject>
	</RawObjects>
</RawMarkup>
